fastpg/__init__.py
fastpg/core.py
fastpg/exceptions.py
fastpg/utils.py
fastpg-0.0.6.dist-info/METADATA
fastpg-0.0.6.dist-info/WHEEL
fastpg-0.0.6.dist-info/licenses/LICENSE
fastpg-0.0.6.dist-info/RECORD
