Metadata-Version: 2.1
Name: fastpg
Version: 0.0.6
Summary: A fast Postgres client library for Python
Project-URL: Homepage, https://github.com/waydegg/fastpg
Project-URL: Source, https://github.com/waydegg/fastpg
Author-email: Wayde Gilliam <waydegilliam@gmail.com>
License: MIT
License-File: LICENSE
Keywords: asyncio,asyncpg,postgres,python
Classifier: Development Status :: 3 - Alpha
Classifier: Environment :: Console
Classifier: Framework :: AsyncIO
Classifier: Intended Audience :: Developers
Classifier: License :: OSI Approved :: MIT License
Classifier: Operating System :: MacOS
Classifier: Operating System :: POSIX :: Linux
Classifier: Programming Language :: Python :: 3 :: Only
Classifier: Programming Language :: Python :: 3.10
Classifier: Programming Language :: Python :: 3.11
Classifier: Topic :: Database :: Front-Ends
Classifier: Topic :: Software Development :: Libraries :: Python Modules
Requires-Python: >=3.10.4
Requires-Dist: asyncpg==0.27.0
Provides-Extra: dev
Requires-Dist: black; extra == 'dev'
Requires-Dist: ipdb; extra == 'dev'
Requires-Dist: ipython; extra == 'dev'
Requires-Dist: isort; extra == 'dev'
